mex/MatchExpression.py
mex/MexAPI.py
mex/MexBuiltInTypes.py
mex/MexUnitTest.py
mex-1.7.1.dist-info/METADATA
mex-1.7.1.dist-info/WHEEL
mex-1.7.1.dist-info/top_level.txt
mex-1.7.1.dist-info/RECORD
