Metadata-Version: 2.1
Name: mex
Version: 1.7.1
Summary: Match Expression
Home-page: UNKNOWN
Author: nwae
Author-email: mapktah@ya.ru
License: UNKNOWN
Platform: UNKNOWN
Requires-Dist: nwae.utils
